Metadata-Version: 1.1
Name: outrigger
Version: 1.1.1
Summary: Outrigger detects *de novo* exons and quantifies their percent spliced-in
Home-page: https://yeolab.github.io/outrigger
Author: Olga Botvinnik
Author-email: olga.botvinnik@gmail.com
License: BSD
Keywords: outrigger,bioinformatics,splicing
Platform: UNKNOWN
Classifier: License :: OSI Approved :: BSD License
Classifier: Natural Language :: English
Classifier: Programming Language :: Python :: 2
Classifier: Programming Language :: Python :: 2.7
Classifier: Programming Language :: Python :: 3
Classifier: Programming Language :: Python :: 3.4
Classifier: Programming Language :: Python :: 3.5
Classifier: Programming Language :: Python :: 3.6
